vacuum/__init__.py
vacuum/cleaner.py
vacuum/cleaner_small.py
vacuum/example.py
vacuum/export.py
vacuum/io.py
vacuum/io_.py
vacuum/main.py
vacuum/manual.py
vacuum/model.py
vacuum/stitch.py
vacuum/test.py
vacuum/trainer.py
vacuum/util.py
vacuum_cleaner-0.3.dist-info/METADATA
vacuum_cleaner-0.3.dist-info/RECORD
vacuum_cleaner-0.3.dist-info/WHEEL
vacuum_cleaner-0.3.dist-info/entry_points.txt
vacuum_cleaner-0.3.dist-info/top_level.txt
