Metadata-Version: 2.1
Name: vacuum-cleaner
Version: 0.3
Summary: Deep Vacuum Cleaner
Home-page: https://github.com/gijzelaerr/vacuum-cleaner
Author: Gijs Molenaar
Author-email: gijs@pythonic.nl
License: MIT
Keywords: radio astronomy deep learning cleaning science
Platform: UNKNOWN
Classifier: License :: OSI Approved :: MIT License
Classifier: Development Status :: 3 - Alpha
Classifier: Programming Language :: Python
Classifier: Programming Language :: Python :: 3.6
Classifier: Programming Language :: Python :: 3.7
Classifier: Intended Audience :: Science/Research
Classifier: Topic :: Scientific/Engineering :: Artificial Intelligence
Classifier: Topic :: Scientific/Engineering :: Astronomy
Provides-Extra: gpu
Requires-Dist: tensorflow
Requires-Dist: astropy
Requires-Dist: scipy
Requires-Dist: pathlib
Requires-Dist: future
Requires-Dist: six
Requires-Dist: typing
Requires-Dist: repoze.lru
Provides-Extra: gpu
Requires-Dist: tensorflow-gpu; extra == 'gpu'
